<?xml version="1.0" encoding="utf-8" ?>
<c2layout>
    <name>Start Screen</name>
    <sid>8224918530848854</sid>
    <event-sheet>Event Start</event-sheet>
    <size>
        <width>800</width>
        <height>600</height>
    </size>
    <margins>
        <horizontal>500</horizontal>
        <vertical>500</vertical>
    </margins>
    <unbounded-scrolling>0</unbounded-scrolling>
    <layers>
        <layer name="Layer 0" sid="5024770188103771">
            <initially-visible>1</initially-visible>
            <background-color>255,255,255</background-color>
            <transparent>0</transparent>
            <parallax>
                <x>1</x>
                <y>1</y>
            </parallax>
            <zoom-rate>1</zoom-rate>
            <opacity>1</opacity>
            <force-own-texture>0</force-own-texture>
            <global>0</global>
            <use-render-cells>0</use-render-cells>
            <blend-mode>0</blend-mode>
            <effect-fallback>0</effect-fallback>
            <instances>
                <instance type="TiledBackground2" uid="60">
                    <properties>
                        <initial-visibility>Visible</initial-visibility>
                        <hotspot>Top-left</hotspot>
                    </properties>
                    <blend-mode>0</blend-mode>
                    <effect-fallback>0</effect-fallback>
                    <world>
                        <x>0</x>
                        <y>0</y>
                        <z>0</z>
                        <width>804</width>
                        <height>606</height>
                        <depth>0</depth>
                        <hotspotX>0</hotspotX>
                        <hotspotY>0</hotspotY>
                        <angle>0</angle>
                        <opacity>1</opacity>
                    </world>
                </instance>
                <instance type="ButtonL1" uid="134">
                    <properties>
                        <type>Button</type>
                        <text>Start Level 1</text>
                        <tooltip></tooltip>
                        <initial-visibility>Visible</initial-visibility>
                        <enabled>Yes</enabled>
                        <auto-font-size>Yes</auto-font-size>
                        <id-optional></id-optional>
                        <checked>No</checked>
                    </properties>
                    <blend-mode>0</blend-mode>
                    <effect-fallback>0</effect-fallback>
                    <world>
                        <x>64</x>
                        <y>224</y>
                        <z>0</z>
                        <width>96</width>
                        <height>32</height>
                        <depth>0</depth>
                        <hotspotX>0</hotspotX>
                        <hotspotY>0</hotspotY>
                    </world>
                </instance>
                <instance type="ButtonL2" uid="135">
                    <properties>
                        <type>Button</type>
                        <text>Start Level 2</text>
                        <tooltip></tooltip>
                        <initial-visibility>Visible</initial-visibility>
                        <enabled>Yes</enabled>
                        <auto-font-size>Yes</auto-font-size>
                        <id-optional></id-optional>
                        <checked>No</checked>
                    </properties>
                    <blend-mode>0</blend-mode>
                    <effect-fallback>0</effect-fallback>
                    <world>
                        <x>64</x>
                        <y>288</y>
                        <z>0</z>
                        <width>96</width>
                        <height>32</height>
                        <depth>0</depth>
                        <hotspotX>0</hotspotX>
                        <hotspotY>0</hotspotY>
                    </world>
                </instance>
                <instance type="ButtonL3" uid="143">
                    <properties>
                        <type>Button</type>
                        <text>Start Level 3</text>
                        <tooltip></tooltip>
                        <initial-visibility>Visible</initial-visibility>
                        <enabled>Yes</enabled>
                        <auto-font-size>Yes</auto-font-size>
                        <id-optional></id-optional>
                        <checked>No</checked>
                    </properties>
                    <blend-mode>0</blend-mode>
                    <effect-fallback>0</effect-fallback>
                    <world>
                        <x>64</x>
                        <y>352</y>
                        <z>0</z>
                        <width>96</width>
                        <height>32</height>
                        <depth>0</depth>
                        <hotspotX>0</hotspotX>
                        <hotspotY>0</hotspotY>
                    </world>
                </instance>
                <instance type="TextLayoutDesc" uid="144">
                    <properties>
                        <text>Go Straight To Level 1</text>
                        <initial-visibility>Invisible</initial-visibility>
                        <font>Showcard Gothic,-29,400,0</font>
                        <color>204,51,255</color>
                        <horizontal-alignment>Center</horizontal-alignment>
                        <vertical-alignment>Top</vertical-alignment>
                        <hotspot>Top-left</hotspot>
                        <wrapping>Word</wrapping>
                        <line-height>0</line-height>
                    </properties>
                    <blend-mode>0</blend-mode>
                    <effect-fallback>0</effect-fallback>
                    <world>
                        <x>352</x>
                        <y>352</y>
                        <z>0</z>
                        <width>448</width>
                        <height>64</height>
                        <depth>0</depth>
                        <hotspotX>0</hotspotX>
                        <hotspotY>0</hotspotY>
                        <angle>0</angle>
                        <opacity>1</opacity>
                    </world>
                </instance>
                <instance type="TextLayoutTitle" uid="147">
                    <properties>
                        <text>Go Straight To Level 2</text>
                        <initial-visibility>Invisible</initial-visibility>
                        <font>Showcard Gothic,-29,400,0</font>
                        <color>204,51,255</color>
                        <horizontal-alignment>Center</horizontal-alignment>
                        <vertical-alignment>Top</vertical-alignment>
                        <hotspot>Top-left</hotspot>
                        <wrapping>Word</wrapping>
                        <line-height>0</line-height>
                    </properties>
                    <blend-mode>0</blend-mode>
                    <effect-fallback>0</effect-fallback>
                    <world>
                        <x>384</x>
                        <y>352</y>
                        <z>0</z>
                        <width>384</width>
                        <height>64</height>
                        <depth>0</depth>
                        <hotspotX>0</hotspotX>
                        <hotspotY>0</hotspotY>
                        <angle>0</angle>
                        <opacity>1</opacity>
                    </world>
                </instance>
                <instance type="TextStartL3" uid="148">
                    <properties>
                        <text>Go Straight To Level 3</text>
                        <initial-visibility>Invisible</initial-visibility>
                        <font>Showcard Gothic,-29,400,0</font>
                        <color>204,51,255</color>
                        <horizontal-alignment>Center</horizontal-alignment>
                        <vertical-alignment>Top</vertical-alignment>
                        <hotspot>Top-left</hotspot>
                        <wrapping>Word</wrapping>
                        <line-height>0</line-height>
                    </properties>
                    <blend-mode>0</blend-mode>
                    <effect-fallback>0</effect-fallback>
                    <world>
                        <x>384</x>
                        <y>352</y>
                        <z>0</z>
                        <width>384</width>
                        <height>64</height>
                        <depth>0</depth>
                        <hotspotX>0</hotspotX>
                        <hotspotY>0</hotspotY>
                        <angle>0</angle>
                        <opacity>1</opacity>
                    </world>
                </instance>
            </instances>
            <effects />
        </layer>
    </layers>
    <nonworld-instances />
    <effects />
</c2layout>
